spar_measure/__init__.py
spar_measure/gui.py
spar_measure/setup.py
spar_measure/util_funcs.py
spar_measure/zca.py
spar_measure/sample_data/favicon.png
spar_measure/sample_data/sample_emb.npy
spar_measure/sample_data/sample_text.csv
spar_measure-0.2.0.dist-info/LICENSE
spar_measure-0.2.0.dist-info/METADATA
spar_measure-0.2.0.dist-info/WHEEL
spar_measure-0.2.0.dist-info/top_level.txt
spar_measure-0.2.0.dist-info/RECORD
