Metadata-Version: 2.1
Name: spar-measure
Version: 0.2.0
Summary: SPAR: Semantic Projection with Active Retrieval
Author-email: Feng Mai <maifeng@gmail.com>
Project-URL: Homepage, https://github.com/maifeng/SPAR_measure
Project-URL: Bug Tracker, https://github.com/maifeng/SPAR_measure/issues
Classifier: Programming Language :: Python :: 3
Classifier: Operating System :: OS Independent
Requires-Python: >=3.8
License-File: LICENSE
Requires-Dist: openai >=1.2.0
Requires-Dist: fire >=0.4.0
Requires-Dist: gradio <4,>=3.47.1
Requires-Dist: numpy >=1.21
Requires-Dist: pandas >=1.3.1
Requires-Dist: scikit-learn >=1.2.1
Requires-Dist: scipy >=1.10.1
Requires-Dist: tqdm >=4.64.0
Requires-Dist: fsspec >=2023.3.0
Requires-Dist: setuptools >=45.2.0
Requires-Dist: torch >=1.8.1
Requires-Dist: transformers >=4.20.1
Requires-Dist: typing-extensions >=4.8.0
Requires-Dist: tenacity >=8.0.1
